aop/__init__.py
aop/api/__init__.py
alibaba_aop-1.0.0.dist-info/METADATA
alibaba_aop-1.0.0.dist-info/WHEEL
alibaba_aop-1.0.0.dist-info/top_level.txt
alibaba_aop-1.0.0.dist-info/RECORD
