Metadata-Version: 2.1
Name: alibaba_aop
Version: 1.0.0
Summary: Alibaba AOP SDK
Author: Fhhhhh
Author-email: 1729219134@qq.com
